[
  {
    "type": "HANA",
    "tags": [
      "alp-minerva-analytics-svc",
      "alp-minerva-db-mgmt-svc",
      "analytics",
      "config2",
      "cdw",
      "alp-sqleditor"
    ],
    "name": "ALPDEV",
    "key": "mridb",
    "description": "",
    "values": {
      "credentials": {
        "user": "TENANT_WRITE_USER",
        "password": "",
        "adminUser": "TENANT_ADMIN_USER",
        "adminPassword": "",
        "readUser": "TENANT_READ_USER",
        "readPassword": "",
        "writeUser": "TENANT_WRITE_USER",
        "writePassword": "",
        "cohortWritePassword": ""
      },
      "host": "dummy-hostname.com",
      "port": "39013",
      "code": "ALPDEV",
      "databaseName": "ALPDEV",
      "validateCertificate": true,
      "sslTrustStore": "SSL_TRUST_STORE",
      "probeSchema": "CDMDEFAULT",
      "vocabSchema": "CDMVOCAB",
      "configSchema": "MRI",
      "cdwSchema": "CDMDEFAULT",
      "schema": "CDMDEFAULT",
      "dialect": "hana",
      "encrypt": true,
      "sslCryptoProvider": "sapcrypto",
      "pooling": true,
      "hostnameInCertificate": "dummy-hostname.com",
      "ca": "",
      "useTLS": false,
      "rejectUnauthorized": false,
      "autoCommit": true,
      "enableAuditPolicies": false
    }
  },
  {
    "type": "POSTGRES",
    "tags": ["alp-minerva-db-mgmt-svc", "dbsvc", "alp-sqleditor"],
    "name": "postgres-mri-minerva",
    "key": "mridb",
    "description": "",
    "values": {
      "credentials": {
        "user": "postgres",
        "password": "",
        "adminUser": "postgres_tenant_admin_user",
        "adminPassword": "",
        "readUser": "postgres_tenant_read_user",
        "readPassword": "",
        "writeUser": "postgres_tenant_write_user",
        "writePassword": "",
        "cohortWritePassword": ""
      },
      "host": "localhost",
      "port": "5432",
      "code": "alp",
      "databaseName": "alp",
      "database": "alp",
      "dialect": "postgres",
      "schema": "cdmdefault",
      "connectionTimeoutMillis": 60000,
      "idleInTransactionSessionTimeout": 60000,
      "queryTimeout": 60000,
      "statementTimeout": 60000,
      "max": 50,
      "idleTimeoutMillis": 300000
    }
  }
]
